aqueduct_executor/__init__.py
aqueduct_executor/operators/__init__.py
aqueduct_executor/operators/connectors/__init__.py
aqueduct_executor/operators/connectors/tabular/__init__.py
aqueduct_executor/operators/connectors/tabular/azure_sql.py
aqueduct_executor/operators/connectors/tabular/bigquery.py
aqueduct_executor/operators/connectors/tabular/common.py
aqueduct_executor/operators/connectors/tabular/config.py
aqueduct_executor/operators/connectors/tabular/connector.py
aqueduct_executor/operators/connectors/tabular/extract.py
aqueduct_executor/operators/connectors/tabular/load.py
aqueduct_executor/operators/connectors/tabular/main.py
aqueduct_executor/operators/connectors/tabular/maria_db.py
aqueduct_executor/operators/connectors/tabular/models.py
aqueduct_executor/operators/connectors/tabular/mysql.py
aqueduct_executor/operators/connectors/tabular/postgres.py
aqueduct_executor/operators/connectors/tabular/redshift.py
aqueduct_executor/operators/connectors/tabular/relational.py
aqueduct_executor/operators/connectors/tabular/s3.py
aqueduct_executor/operators/connectors/tabular/salesforce.py
aqueduct_executor/operators/connectors/tabular/snowflake.py
aqueduct_executor/operators/connectors/tabular/spec.py
aqueduct_executor/operators/connectors/tabular/sql_server.py
aqueduct_executor/operators/connectors/tabular/sqlite.py
aqueduct_executor/operators/connectors/tests/__init__.py
aqueduct_executor/operators/connectors/tests/conf.py
aqueduct_executor/operators/connectors/tests/conftest.py
aqueduct_executor/operators/connectors/tests/test_bigquery.py
aqueduct_executor/operators/connectors/tests/test_mariadb.py
aqueduct_executor/operators/connectors/tests/test_mysql.py
aqueduct_executor/operators/connectors/tests/test_postgres.py
aqueduct_executor/operators/connectors/tests/test_redshift.py
aqueduct_executor/operators/connectors/tests/test_snowflake.py
aqueduct_executor/operators/connectors/tests/test_sql_server.py
aqueduct_executor/operators/connectors/tests/test_sqlite.py
cgwu_test_server-0.0.1.dist-info/METADATA
cgwu_test_server-0.0.1.dist-info/WHEEL
cgwu_test_server-0.0.1.dist-info/top_level.txt
cgwu_test_server-0.0.1.dist-info/RECORD
