Metadata-Version: 2.1
Name: cgwu-test-server
Version: 0.0.1
Summary: Aqueduct OSS backend.
Home-page: https://www.aqueducthq.com/
Author: Aqueduct, Inc.
Author-email: support@aqueducthq.com
License: Apache License 2.0
Classifier: Programming Language :: Python :: 3
Requires-Python: >=3.7,<=3.10
Requires-Dist: boto3
Requires-Dist: cloudpickle
Requires-Dist: numpy
Requires-Dist: pandas
Requires-Dist: pydantic
Requires-Dist: SQLAlchemy
Requires-Dist: distro
Requires-Dist: pyyaml
Requires-Dist: cgwu-test-upload-1
